orthogonium/VERSION
orthogonium/__init__.py
orthogonium/losses.py
orthogonium/reparametrizers.py
orthogonium/layers/__init__.py
orthogonium/layers/channel_shuffle.py
orthogonium/layers/custom_activations.py
orthogonium/layers/normalization.py
orthogonium/layers/residual.py
orthogonium/layers/conv/__init__.py
orthogonium/layers/conv/init.py
orthogonium/layers/conv/AOC/__init__.py
orthogonium/layers/conv/AOC/bcop_x_rko_conv.py
orthogonium/layers/conv/AOC/fast_block_ortho_conv.py
orthogonium/layers/conv/AOC/ortho_conv.py
orthogonium/layers/conv/AOC/rko_conv.py
orthogonium/layers/conv/AOL/__init__.py
orthogonium/layers/conv/AOL/aol.py
orthogonium/layers/conv/SLL/__init__.py
orthogonium/layers/conv/SLL/sll_layer.py
orthogonium/layers/conv/adaptiveSOC/__init__.py
orthogonium/layers/conv/adaptiveSOC/fast_skew_ortho_conv.py
orthogonium/layers/conv/adaptiveSOC/ortho_conv.py
orthogonium/layers/conv/adaptiveSOC/soc_x_rko_conv.py
orthogonium/layers/conv/singular_values/__init__.py
orthogonium/layers/conv/singular_values/delattre24.py
orthogonium/layers/conv/singular_values/get_sv.py
orthogonium/layers/linear/__init__.py
orthogonium/layers/linear/ortho_linear.py
orthogonium/legacy/__init__.py
orthogonium/legacy/block_ortho_conv.py
orthogonium/legacy/cayley_ortho_conv.py
orthogonium/legacy/skew_ortho_conv.py
orthogonium/model_factory/__init__.py
orthogonium/model_factory/classparam.py
orthogonium/model_factory/models_factory.py
orthogonium-0.0.4.dist-info/licenses/LICENSE
orthogonium-0.0.4.dist-info/METADATA
orthogonium-0.0.4.dist-info/WHEEL
orthogonium-0.0.4.dist-info/top_level.txt
orthogonium-0.0.4.dist-info/RECORD
